m3gp/GeneticOperators.py
m3gp/Individual.py
m3gp/M3GP.py
m3gp/MahalanobisDistanceClassifier.py
m3gp/Node.py
m3gp/__init__.py
m3gp-1.2.0.dist-info/METADATA
m3gp-1.2.0.dist-info/WHEEL
m3gp-1.2.0.dist-info/top_level.txt
m3gp-1.2.0.dist-info/RECORD
